Screen_Any.py
Screen_Any-1.0.0.dist-info/METADATA
Screen_Any-1.0.0.dist-info/RECORD
Screen_Any-1.0.0.dist-info/WHEEL
Screen_Any-1.0.0.dist-info/top_level.txt
